particleanalyzer/__init__.py
particleanalyzer/app.py
particleanalyzer/cli.py
particleanalyzer/version.py
particleanalyzer/assets/instruction.mp4
particleanalyzer/assets/icon/ai-white.png
particleanalyzer/assets/icon/ai.jpg
particleanalyzer/assets/icon/ai.png
particleanalyzer/assets/icon/dislike-white.png
particleanalyzer/assets/icon/dislike.png
particleanalyzer/assets/icon/favicon.png
particleanalyzer/assets/icon/favicon.svg
particleanalyzer/assets/icon/icons8-метла-50-white.png
particleanalyzer/assets/icon/icons8-метла-50.png
particleanalyzer/assets/icon/icons8-химия-50-white.png
particleanalyzer/assets/icon/icons8-химия-50.png
particleanalyzer/assets/icon/incorrect-white.png
particleanalyzer/assets/icon/incorrect.png
particleanalyzer/assets/icon/like-white.png
particleanalyzer/assets/icon/like.png
particleanalyzer/assets/themes/theme_schema@0.0.1.json
particleanalyzer/core/CustomDetectron2Model.py
particleanalyzer/core/Detectron2Loader.py
particleanalyzer/core/EnhancementPipeline.py
particleanalyzer/core/ImageEnhancement.py
particleanalyzer/core/ImagePreprocessor.py
particleanalyzer/core/LLMAnalysis.py
particleanalyzer/core/ModelManager.py
particleanalyzer/core/ONNXLoader.py
particleanalyzer/core/ParticleAnalyzer.py
particleanalyzer/core/PointManager.py
particleanalyzer/core/ScaleProcessor.py
particleanalyzer/core/StatisticsBuilder.py
particleanalyzer/core/YOLOLoader.py
particleanalyzer/core/__init__.py
particleanalyzer/core/about.py
particleanalyzer/core/language_context.py
particleanalyzer/core/languages.py
particleanalyzer/core/parameter_information.py
particleanalyzer/core/ui.py
particleanalyzer/core/ui_styles.py
particleanalyzer/core/utils.py
particleanalyzer-1.4.1.dist-info/licenses/LICENSE
particleanalyzer-1.4.1.dist-info/METADATA
particleanalyzer-1.4.1.dist-info/WHEEL
particleanalyzer-1.4.1.dist-info/entry_points.txt
particleanalyzer-1.4.1.dist-info/top_level.txt
particleanalyzer-1.4.1.dist-info/RECORD
