Metadata-Version: 2.4
Name: ParticleAnalyzer
Version: 1.4.1
Summary: SEM Image Analysis Tool
Author-email: Kirill Rybakov <rybakov-ks@ya.ru>
Maintainer-email: Kirill Rybakov <rybakov-ks@ya.ru>
License: GPL-3.0
Project-URL: Homepage, https://github.com/rybakov-ks/ParticleAnalyzer
Project-URL: Documentation, https://github.com/rybakov-ks/ParticleAnalyzer#readme
Project-URL: Repository, https://github.com/rybakov-ks/ParticleAnalyzer.git
Project-URL: Bug Tracker, https://github.com/rybakov-ks/ParticleAnalyzer/issues
Project-URL: Live Demo, https://particleanalyzer.ru
Project-URL: Telegram Bot, https://t.me/particleanalyzer_bot
Keywords: SEM,microscopy,image-analysis,particle-analysis,materials-science,nanoparticles,computer-vision,opencv,python,scientific-computing,microstructure,particle-size,image-processing,detectron2,YOLO,deep-learning,microscope-images,material-characterization,automated-measurements,research-tools
Classifier: Development Status :: 5 - Production/Stable
Classifier: Intended Audience :: Science/Research
Classifier: License :: OSI Approved :: GNU General Public License v3 (GPLv3)
Classifier: Operating System :: OS Independent
Classifier: Programming Language :: Python :: 3
Classifier: Programming Language :: Python :: 3.10
Classifier: Programming Language :: Python :: 3.11
Classifier: Programming Language :: Python :: 3.12
Classifier: Topic :: Scientific/Engineering :: Image Processing
Classifier: Topic :: Scientific/Engineering :: Physics
Classifier: Topic :: Scientific/Engineering :: Chemistry
Classifier: Topic :: Scientific/Engineering :: Artificial Intelligence
Requires-Python: >=3.10
License-File: LICENSE
Requires-Dist: gradio==5.50.0
Requires-Dist: gradio_imagemeasurement
Requires-Dist: gradio-rangeslider
Requires-Dist: matplotlib
Requires-Dist: opencv-python
Requires-Dist: opencv-python-headless
Requires-Dist: Pillow
Requires-Dist: plotly
Requires-Dist: sahi
Requires-Dist: scipy
Requires-Dist: tqdm
Requires-Dist: ultralytics>=8.4.7
Requires-Dist: huggingface_hub
Requires-Dist: openai
Requires-Dist: Requests
Requires-Dist: numpy
Requires-Dist: pandas
Requires-Dist: supervision
Requires-Dist: easyocr
Requires-Dist: onnxruntime
Provides-Extra: dev
Requires-Dist: pytest>=7.0.0; extra == "dev"
Requires-Dist: pytest-cov>=4.0.0; extra == "dev"
Requires-Dist: black>=23.0.0; extra == "dev"
Requires-Dist: flake8>=6.0.0; extra == "dev"
Requires-Dist: mypy>=1.0.0; extra == "dev"
Requires-Dist: pre-commit>=3.0.0; extra == "dev"
Requires-Dist: isort>=5.12.0; extra == "dev"
Provides-Extra: docs
Requires-Dist: sphinx>=6.0.0; extra == "docs"
Requires-Dist: sphinx-rtd-theme>=1.2.0; extra == "docs"
Requires-Dist: myst-parser>=1.0.0; extra == "docs"
Dynamic: license-file
